LICENSE
sniptly/__init__.py
sniptly/cli.py
sniptly/config.py
sniptly/file_line_wrapper.py
sniptly/output.py
sniptly/snippet_functions.py
sniptly/string_manipulation.py
sniptly/types.py
sniptly/utils.py
sniptly-0.1.25.dist-info/entry_points.txt
sniptly-0.1.25.dist-info/LICENSE
sniptly-0.1.25.dist-info/WHEEL
sniptly-0.1.25.dist-info/METADATA
sniptly-0.1.25.dist-info/RECORD
