Metadata-Version: 2.1
Name: sniptly
Version: 0.1.25
Summary: Build code snippets for vscode
Home-page: https://github.com/jjaakko/sniptly
License: MIT
Keywords: vscode,code snippets,productivity
Author: jjaakko
Author-email: devjaakko@gmail.com
Requires-Python: >=3.8,<4.0
Classifier: Development Status :: 2 - Pre-Alpha
Classifier: Environment :: Console
Classifier: Intended Audience :: Developers
Classifier: License :: OSI Approved :: MIT License
Classifier: Operating System :: OS Independent
Classifier: Programming Language :: Python :: 3
Classifier: Programming Language :: Python :: 3.8
Classifier: Programming Language :: Python :: 3.9
Classifier: Topic :: Software Development
Requires-Dist: appdirs (>=1.4.4,<2.0.0)
Requires-Dist: click (>=7.1.2,<8.0.0)
Requires-Dist: jstyleson (>=0.0.2,<0.0.3)
Requires-Dist: rich (>=10.3.0,<11.0.0)
Requires-Dist: toml (>=0.10.2,<0.11.0)
Project-URL: Repository, https://github.com/jjaakko/sniptly
